pyllars/__init__.py
pyllars/collection_utils.py
pyllars/dask_utils.py
pyllars/deprecated_decorator.py
pyllars/external_sparse_matrix_list.py
pyllars/gene_ontology_utils.py
pyllars/hyperparameter_utils.py
pyllars/incremental_gaussian_estimator.py
pyllars/latex_utils.py
pyllars/logging_utils.py
pyllars/math_utils.py
pyllars/matrix_utils.py
pyllars/missing_data_utils.py
pyllars/ml_utils.py
pyllars/mpl_utils.py
pyllars/mygene_utils.py
pyllars/nlp_utils.py
pyllars/pandas_utils.py
pyllars/physionet_utils.py
pyllars/scip_utils.py
pyllars/shell_utils.py
pyllars/sparse_vector.py
pyllars/ssh_utils.py
pyllars/stats_utils.py
pyllars/string_utils.py
pyllars/suppress_stdout_stderr.py
pyllars/utils.py
pyllars/validation_utils.py
pyllars/xgboost_utils.py
pyllars/sklearn_transformers/__init__.py
pyllars/sklearn_transformers/incremental_count_vectorizer.py
pyllars/sklearn_transformers/multicolumn_imputer.py
pyllars/sklearn_transformers/multicolumn_label_encoder.py
pyllars/sklearn_transformers/nan_label_encoder.py
pyllars/sklearn_transformers/nan_nearest_neighbors.py
pyllars/sklearn_transformers/nan_one_hot_encoder.py
pyllars/sklearn_transformers/nan_standard_scaler.py
pyllars/sklearn_transformers/simple_numeric_bow_union.py
pyllars/torch/__init__.py
pyllars/torch/torch_model_trainer.py
pyllars/torch/torch_utils.py
pyllars-1.0.5.dist-info/LICENSE
pyllars-1.0.5.dist-info/METADATA
pyllars-1.0.5.dist-info/WHEEL
pyllars-1.0.5.dist-info/top_level.txt
pyllars-1.0.5.dist-info/RECORD
