Metadata-Version: 2.1
Name: pyllars
Version: 1.0.5
Summary: This package contains supporting utilities for Python 3.
Home-page: https://github.com/bmmalone/pyllars
Author: Brandon Malone
Author-email: bmmalone@gmail.com
License: MIT
Keywords: utilities
Classifier: License :: OSI Approved :: MIT License
Classifier: Programming Language :: Python :: 3
License-File: LICENSE
Requires-Dist: cython
Requires-Dist: dask[complete]
Requires-Dist: docopt
Requires-Dist: graphviz
Requires-Dist: joblib
Requires-Dist: matplotlib
Requires-Dist: matplotlib-venn
Requires-Dist: more-itertools
Requires-Dist: networkx (>=2.0)
Requires-Dist: nltk
Requires-Dist: numpy
Requires-Dist: openpyxl
Requires-Dist: pandas
Requires-Dist: paramiko
Requires-Dist: pydot
Requires-Dist: requests
Requires-Dist: scipy
Requires-Dist: seaborn
Requires-Dist: six
Requires-Dist: scikit-learn
Requires-Dist: sklearn-pandas
Requires-Dist: spur
Requires-Dist: statsmodels
Requires-Dist: tables
Requires-Dist: tqdm
Requires-Dist: xgboost
Requires-Dist: xlrd
Provides-Extra: all
Requires-Dist: pytest ; extra == 'all'
Requires-Dist: coverage ; extra == 'all'
Requires-Dist: pytest-cov ; extra == 'all'
Requires-Dist: coveralls ; extra == 'all'
Requires-Dist: pytest-runner ; extra == 'all'
Requires-Dist: fastparquet ; extra == 'all'
Requires-Dist: goatools ; extra == 'all'
Requires-Dist: mygene ; extra == 'all'
Requires-Dist: biopython ; extra == 'all'
Requires-Dist: torch ; extra == 'all'
Requires-Dist: torchvision ; extra == 'all'
Requires-Dist: ray[tune] ; extra == 'all'
Requires-Dist: sphinx ; extra == 'all'
Requires-Dist: sphinx-rtd-theme ; extra == 'all'
Requires-Dist: twine ; extra == 'all'
Requires-Dist: readme-renderer[md] ; extra == 'all'
Provides-Extra: bio
Requires-Dist: goatools ; extra == 'bio'
Requires-Dist: mygene ; extra == 'bio'
Requires-Dist: biopython ; extra == 'bio'
Provides-Extra: docs
Requires-Dist: sphinx ; extra == 'docs'
Requires-Dist: sphinx-rtd-theme ; extra == 'docs'
Provides-Extra: parquest
Requires-Dist: fastparquet ; extra == 'parquest'
Provides-Extra: pypi
Requires-Dist: twine ; extra == 'pypi'
Requires-Dist: readme-renderer[md] ; extra == 'pypi'
Provides-Extra: setup
Requires-Dist: pytest-runner ; extra == 'setup'
Provides-Extra: test
Requires-Dist: pytest ; extra == 'test'
Requires-Dist: coverage ; extra == 'test'
Requires-Dist: pytest-cov ; extra == 'test'
Requires-Dist: coveralls ; extra == 'test'
Requires-Dist: pytest-runner ; extra == 'test'
Provides-Extra: torch
Requires-Dist: torch ; extra == 'torch'
Requires-Dist: torchvision ; extra == 'torch'
Requires-Dist: ray[tune] ; extra == 'torch'
